{
  "name": "Howard Larson",
  "age": 59,
  "address": {
    "street": "Majma Circle",
    "city": "Micaifi",
    "state": "WA",
    "zip": "05020"
  },
  "contact": {
    "phone": "(731) 306-6206",
    "servicePhone": "800328362"
  },
  "birthday": "1979-05-26T21:07:57.186Z",
  "ip": "3.231.233.18",
  "foo": "bar",
  "profile": {
    "about": "Go ohabel pih da ride bunagom weiw tozpet caprahme toros hilumed cutcer dizpib dicimsel di. Kem jorpi fam gena aje wikgi nep id no agmuwa vow gim sumitu bebotcit zutoz moseptun cet sacculabe. Bufe tivsorpe dogol uvawuhra ropeduz ezajiug hoj le vej nig ilacan cempucibe ava opko ol og miresa jefbom. Cuw kawsiil kibfa alo toilhoh zopze su ub suljos umusafwa der ucgebulu cunuc eje jepi hiwi. Kaw bo lammuve jueguho ja beku nej hawlum hajuz irzizef beuce evomaet durumeoce ebtefig wenho jave. Ke piv lasva midievu hot ab cad davivoh ala nizuwovow ucupugte cidika re miig ad gu lookodih gievo. Omuno kohime siunpe uc roba vuwip higik pamhi da cuzpucu utfogal nerub duzit.",
    "bio": "Kafdicofe peb daoksob ke kah latauc kucmowbo cahet zojijcad vol jolep odaba totvemi ja mapi wukmimzam. Gospata rek vacik res dimde guhisin ze opdovzi uwocuwo so col sosesjaw jos laz kakrotluz ruubfiw. Mijoj degjas oz lintas ofo gafesoz sopu roj dokbol osupides kejpawit ofvuune fucis ize upu ibu fazcu ciwiluh. Vesofis upiot cis rehofani wud dohzec akid unusi tujzak dur ipzazaki mu buspu el sut bah ocumoc fafrekas."
  },
  "apiKey": "fa738052bcb1921971b0355be2db6878f53c183854f197987a2e78f909e8b383",
  "currency": {
    "code": "KRW",
    "name": "Korea (South) Won"
  }
}