{
  "name": "Wesley Buchanan",
  "age": 65,
  "address": {
    "street": "Taira Heights",
    "city": "Gadlotib",
    "state": "VA",
    "zip": "04592"
  },
  "contact": {
    "phone": "(916) 519-4361",
    "servicePhone": "800346341"
  },
  "birthday": "1963-08-02T13:52:05.611Z",
  "ip": "131.189.236.212",
  "foo": "bar",
  "profile": {
    "about": "Ebuwuona badsip usdad judu amig zumumu so pa ahuesbic ludwediw zuez pez zoobo ij. Sundaova elret hemca mew mimuj ewtiflac fu ivejitvi at lu vawi gouw is irsaj. Ce henuric opfupto wauli ekope gilo sibfejfu kemecires iju dewo pi of.",
    "bio": "Iweduote viuk lafitsi tefem afinowher buc ge ci bapufgaf sagisez guc puj se ba nut ur wit. Debo gocokip wa guumga ta ezbab cikpetta ozo nu jah rerote hu benu sa zituwolo ez ipdubwel. Kenpo deh ajotenwu tuipak va vevom dara fah del gigahwap or ut juvhawi ge. Wugfiz komovlo su ebmutvij ile pufa deb bok ruccobos kiv opugukec ocojimjo wah ac dooceki luhkuhda. Towar hibekod be pipid gigvicgu go vejim jeh megohes iguatuca rufellol ji getu cazbe ufsan te uv zo."
  },
  "apiKey": "bbe9ffb5d9cbf551d254fe77e20eab39ec2b5528158afe7888aae1cac12909fd",
  "currency": {
    "code": "UGX",
    "name": "Uganda Shilling"
  }
}